app/__init__.py
app/database/__init__.py
app/database/database.py
app/docker_container/__init__.py
app/docker_container/docker_container.py
app/exceptions/__init__.py
app/exceptions/container_not_started.py
app/exceptions/db_init_took_too_long.py
app/exceptions/postgres_init.py
app/models/__init__.py
app/models/database_configuration.py
app/sqlalchemy_package/postgres.py
app/types/sqlalchemy/new_row.py
app/types/sqlalchemy/new_row_dict.py
edbintt-0.2.0.dist-info/METADATA
edbintt-0.2.0.dist-info/WHEEL
edbintt-0.2.0.dist-info/licenses/LICENSE
edbintt-0.2.0.dist-info/RECORD
