Metadata-Version: 2.1
Name: edbintt
Version: 0.2.0
Summary: Easy Database Integration Testing
Project-URL: homepage, https://gitlab.com/doublethink13/edbintt/
Project-URL: repository, https://gitlab.com/doublethink13/edbintt/
Author: doublethink13
Maintainer: doublethink13
License: Copyright 2023 doublethink13
License-File: LICENSE
Keywords: database,integration,testing
Classifier: Programming Language :: Python :: 3
Requires-Python: >=3.10
Requires-Dist: docker==6.0.1
Requires-Dist: psycopg2==2.9.6
Requires-Dist: sqlalchemy==2.0.9
Provides-Extra: dev
Requires-Dist: black==22.12.0; extra == 'dev'
Requires-Dist: build==0.10.0; extra == 'dev'
Requires-Dist: coverage==7.2.2; extra == 'dev'
Requires-Dist: flake8==6.0.0; extra == 'dev'
Requires-Dist: isort==5.12.0; extra == 'dev'
Requires-Dist: mypy==1.2.0; extra == 'dev'
Requires-Dist: pre-commit==3.2.2; extra == 'dev'
Requires-Dist: pydantic==1.10.7; extra == 'dev'
Requires-Dist: pytest==7.2.2; extra == 'dev'
Requires-Dist: twine==4.0.2; extra == 'dev'
